{
  "course_name": "국제경영",
  "course_code": "msm201",
  "semester": "2026 Fall",
  "academic_level": "Undergraduate Year 3-4",
  "student_count": "40",
  "professor_name": "Professor Sang Ho Han",
  "delivery_language": "English",
  "language_code": "en",
  "course_folder": "msm201_국제경영_2026 fall",
  "textbook_filename": "",
  "textbook_path": "",
  "textbook_extracted_path": "",
  "grading_policy": {
    "attendance": 20,
    "midterm": 30,
    "final": 30,
    "assignments": 10,
    "attitude": 10,
    "total": 100
  },
  "skip_chapters": [],
  "emphasized_chapters": [],
  "top_3_outcomes": [],
  "lecture_style": "balanced",
  "exam_question_types": "a",
  "assignment_type": "individual",
  "real_world_applications": "",
  "assignment_count": 1,
  "script_detail_level": "beginner",
  "professor_language_proficiency": "beginner",
  "pronunciation_guide": false,
  "improvisation_tips": true,
  "created_at": "2026-04-30T04:52:10.781Z",
  "last_updated": "2026-04-30T04:52:10.781Z",
  "status": {
    "syllabus": "pending",
    "lectures_completed": [],
    "midterm": "pending",
    "final": "pending",
    "assignments_completed": []
  }
}